<annotation>
	<folder>100</folder>
	<filename>105-16-08399_20151225919_10머8471_87781.jpg</filename>
	<path>C:\Users\agilesoda\Desktop\손상박스\2. 190903_front_fender_손상박스_원본\3\100\105-16-08399_20151225919_10머8471_87781.jpg</path>
	<source>
		<database>Unknown</database>
	</source>
	<size>
		<width>800</width>
		<height>600</height>
		<depth>3</depth>
	</size>
	<segmented>0</segmented>
	<object>
		<name>scratch</name>
		<pose>Unspecified</pose>
		<truncated>0</truncated>
		<difficult>0</difficult>
		<bndbox>
			<xmin>552</xmin>
			<ymin>312</ymin>
			<xmax>625</xmax>
			<ymax>370</ymax>
		</bndbox>
	</object>
</annotation>
